centreonapi/__init__.py
centreonapi/centreon.py
centreonapi/webservice/__init__.py
centreonapi/webservice/configuration/__init__.py
centreonapi/webservice/configuration/command.py
centreonapi/webservice/configuration/common.py
centreonapi/webservice/configuration/contact.py
centreonapi/webservice/configuration/downtime.py
centreonapi/webservice/configuration/host.py
centreonapi/webservice/configuration/hostgroups.py
centreonapi/webservice/configuration/poller.py
centreonapi/webservice/configuration/resourcecfg.py
centreonapi/webservice/configuration/service.py
tests/__init__.py
tests/test_command.py
tests/test_hosts.py
tests/test_resourcecfg.py
centreonapi-0.1.7.dist-info/AUTHORS.rst
centreonapi-0.1.7.dist-info/LICENSE
centreonapi-0.1.7.dist-info/METADATA
centreonapi-0.1.7.dist-info/WHEEL
centreonapi-0.1.7.dist-info/top_level.txt
centreonapi-0.1.7.dist-info/RECORD
