Metadata-Version: 2.1
Name: centreonapi
Version: 0.1.7
Summary: Centreon Api for use Webservice in Centreon Web 2.8.0 or later
Home-page: https://github.com/guillaumewatteeux/centreon-sdk-python
Author: Guillaume Watteeux
Author-email: g@15x.fr
License: Apache-2.0
Keywords: centreonapi
Platform: UNKNOWN
Classifier: Development Status :: 2 - Pre-Alpha
Classifier: Intended Audience :: Developers
Classifier: License :: OSI Approved :: Apache Software License
Classifier: Natural Language :: English
Classifier: Programming Language :: Python :: 2
Classifier: Programming Language :: Python :: 2.7
Classifier: Programming Language :: Python :: 3
Classifier: Programming Language :: Python :: 3.5
Classifier: Programming Language :: Python :: 3.6
Requires-Dist: requests
Requires-Dist: bs4
